vilmantas_data_crawler/__init__.py
vilmantas_data_crawler/main.py
vilmantas_data_crawler-0.1.0.dist-info/METADATA
vilmantas_data_crawler-0.1.0.dist-info/WHEEL
vilmantas_data_crawler-0.1.0.dist-info/RECORD
